{
  "id": "char_012",
  "name": "Character_12",
  "rarity": "Rare",
  "rarity_color": "#00aaff",
  "class": "Debuffer",
  "tags": [
    "#Rare",
    "#Debuffer"
  ],
  "abilities": {
    "passive": "Passive ability of Character_12 with role Debuffer.",
    "active": "Active skill of Character_12 unleashing power as a Debuffer.",
    "ultimate": null
  },
  "lore": "Character_12 is a mysterious debuffer who emerged during the collapse of Arklyra. Their journey reveals deep truths of the Nexus."
}